sos_ansible/__init__.py
sos_ansible/__main__.py
sos_ansible/modules/__init__.py
sos_ansible/modules/config_manager.py
sos_ansible/modules/file_handling.py
sos_ansible/modules/locating_sos.py
sos_ansible/modules/parsing.py
sos_ansible/modules/helpers/__init__.py
sos_ansible/modules/helpers/rule_writer.py
sos_ansible/modules/helpers/rule_writer_input.py
sos_ansible/modules/helpers/write_json.py
sos_ansible-1.0.5.dist-info/LICENSE
sos_ansible-1.0.5.dist-info/METADATA
sos_ansible-1.0.5.dist-info/WHEEL
sos_ansible-1.0.5.dist-info/entry_points.txt
sos_ansible-1.0.5.dist-info/top_level.txt
sos_ansible-1.0.5.dist-info/RECORD
