Metadata-Version: 2.1
Name: sos-ansible
Version: 1.0.5
Summary: A sosreport parser for ansible
Author-email: Lucas Benedito <lbenedit@redhat.com>
License: GPL-3.0 license
Project-URL: Homepage, https://github.com/lucas-benedito/sos-ansible
Project-URL: Bug Tracker, https://github.com/lucas-benedito/sos-ansible/issues
Requires-Python: >=3.9
License-File: LICENSE
Requires-Dist: inquirer
Provides-Extra: dev
Requires-Dist: black ; extra == 'dev'
Requires-Dist: pylint ; extra == 'dev'
Requires-Dist: pytest ; extra == 'dev'
Requires-Dist: pip-tools ; extra == 'dev'
